saxo_openapi/__init__.py
saxo_openapi/exceptions.py
saxo_openapi/saxo_openapi.py
saxo_openapi/contrib/__init__.py
saxo_openapi/contrib/session.py
saxo_openapi/contrib/orders/__init__.py
saxo_openapi/contrib/orders/baseorder.py
saxo_openapi/contrib/orders/helper.py
saxo_openapi/contrib/orders/limitorder.py
saxo_openapi/contrib/orders/marketorder.py
saxo_openapi/contrib/orders/mixin.py
saxo_openapi/contrib/orders/onfill.py
saxo_openapi/contrib/orders/stoporder.py
saxo_openapi/contrib/util/__init__.py
saxo_openapi/contrib/util/instrument_to_uic.py
saxo_openapi/contrib/ws/__init__.py
saxo_openapi/contrib/ws/stream.py
saxo_openapi/definitions/__init__.py
saxo_openapi/definitions/accounthistory.py
saxo_openapi/definitions/activities.py
saxo_openapi/definitions/orders.py
saxo_openapi/definitions/reportformats.py
saxo_openapi/endpoints/__init__.py
saxo_openapi/endpoints/apirequest.py
saxo_openapi/endpoints/decorators.py
saxo_openapi/endpoints/accounthistory/__init__.py
saxo_openapi/endpoints/accounthistory/accountvalues.py
saxo_openapi/endpoints/accounthistory/base.py
saxo_openapi/endpoints/accounthistory/historicalpositions.py
saxo_openapi/endpoints/accounthistory/performance.py
saxo_openapi/endpoints/accounthistory/responses/__init__.py
saxo_openapi/endpoints/accounthistory/responses/accountvalues.py
saxo_openapi/endpoints/accounthistory/responses/historicalpositions.py
saxo_openapi/endpoints/accounthistory/responses/performance.py
saxo_openapi/endpoints/chart/__init__.py
saxo_openapi/endpoints/chart/base.py
saxo_openapi/endpoints/chart/charts.py
saxo_openapi/endpoints/chart/responses/__init__.py
saxo_openapi/endpoints/chart/responses/charts.py
saxo_openapi/endpoints/eventnotificationservices/__init__.py
saxo_openapi/endpoints/eventnotificationservices/base.py
saxo_openapi/endpoints/eventnotificationservices/clientactivities.py
saxo_openapi/endpoints/eventnotificationservices/responses/__init__.py
saxo_openapi-0.6.0.dist-info/LICENSE
saxo_openapi-0.6.0.dist-info/METADATA
saxo_openapi-0.6.0.dist-info/WHEEL
saxo_openapi-0.6.0.dist-info/top_level.txt
saxo_openapi-0.6.0.dist-info/RECORD
