Metadata-Version: 1.1
Name: saxo_openapi
Version: 0.6.0
Summary: SAXO Bank OpenAPI REST-API access
Home-page: https://github.com/hootnot/saxo_openapi
Author: Feite Brekeveld
Author-email: f.brekeveld@gmail.com
License: MIT license
Keywords: saxo_openapi
Platform: UNKNOWN
Classifier: Development Status :: 3 - Alpha
Classifier: Topic :: Software Development :: Libraries :: Python Modules
Classifier: Intended Audience :: Developers
Classifier: Intended Audience :: Financial and Insurance Industry
Classifier: License :: OSI Approved :: MIT License
Classifier: Natural Language :: English
Classifier: Programming Language :: Python :: 3
Classifier: Programming Language :: Python :: 3.4
Classifier: Programming Language :: Python :: 3.5
Classifier: Programming Language :: Python :: 3.6
Classifier: Programming Language :: Python :: 3.7
